inputimeout/__init__.py
inputimeout/__version__.py
inputimeout/inputimeout.py
inputimeout-1.0.3.dist-info/DESCRIPTION.rst
inputimeout-1.0.3.dist-info/METADATA
inputimeout-1.0.3.dist-info/RECORD
inputimeout-1.0.3.dist-info/WHEEL
inputimeout-1.0.3.dist-info/metadata.json
inputimeout-1.0.3.dist-info/top_level.txt
tests/__init__.py
tests/test_inputimeout.py
