Metadata-Version: 2.0
Name: inputimeout
Version: 1.0.3
Summary: Multi platform standard input with timeout
Home-page: http://github.com/johejo/inutimeout
Author: Mitsuo Heijo
Author-email: mitsuo_h@outlook.com
License: MIT
Platform: UNKNOWN
Classifier: Development Status :: 4 - Beta
Classifier: Environment :: Console
Classifier: Intended Audience :: Developers
Classifier: License :: OSI Approved :: MIT License
Classifier: Operating System :: MacOS :: MacOS X
Classifier: Operating System :: Microsoft :: Windows
Classifier: Operating System :: POSIX :: Linux
Classifier: Programming Language :: Python :: 3 :: Only
Classifier: Programming Language :: Python :: 3.6
